wpreddit/__init__.py
wpreddit/config.py
wpreddit/connection.py
wpreddit/download.py
wpreddit/ksetwallpaper.py
wpreddit/main.py
wpreddit/reddit.py
wpreddit/wallpaper.py
wpreddit/conf_files/linux-autostart.desktop
wpreddit/conf_files/unix.conf
wpreddit/conf_files/windows.conf
wpreddit/fonts/Cantarell-Regular.otf
rewal-3.2.6.dist-info/LICENSE.txt
rewal-3.2.6.dist-info/METADATA
rewal-3.2.6.dist-info/WHEEL
rewal-3.2.6.dist-info/entry_points.txt
rewal-3.2.6.dist-info/top_level.txt
rewal-3.2.6.dist-info/RECORD
