Metadata-Version: 2.1
Name: rewal
Version: 3.2.6
Summary: A utility that downloads wallpapers from reddit
Home-page: https://www.github.com/iamtalhaasghar/rewal
Author: Talha Asghar
Author-email: talhaasghar.contact@simplelogin.fr
License: UNKNOWN
Platform: UNKNOWN
License-File: LICENSE.txt
Requires-Dist: Pillow (==9.0.1)
Requires-Dist: pywal (==3.3.0)
Requires-Dist: dbus-python (==1.2.18)
